griptape/__init__.py
griptape/flow/__init__.py
griptape/flow/artifacts/__init__.py
griptape/flow/artifacts/error_output.py
griptape/flow/artifacts/structure_artifact.py
griptape/flow/artifacts/text_output.py
griptape/flow/drivers/__init__.py
griptape/flow/drivers/memory/__init__.py
griptape/flow/drivers/memory/disk_memory_driver.py
griptape/flow/drivers/memory/memory_driver.py
griptape/flow/drivers/prompt/__init__.py
griptape/flow/drivers/prompt/base_prompt_driver.py
griptape/flow/drivers/prompt/cohere_prompt_driver.py
griptape/flow/drivers/prompt/hugging_face_hub_prompt_driver.py
griptape/flow/drivers/prompt/hugging_face_pipeline_prompt_driver.py
griptape/flow/drivers/prompt/openai_prompt_driver.py
griptape/flow/memory/__init__.py
griptape/flow/memory/buffer_pipeline_memory.py
griptape/flow/memory/pipeline_memory.py
griptape/flow/memory/pipeline_run.py
griptape/flow/memory/summary_pipeline_memory.py
griptape/flow/rules/__init__.py
griptape/flow/rules/json.py
griptape/flow/rules/meta.py
griptape/flow/rules/rule.py
griptape/flow/schemas/__init__.py
griptape/flow/schemas/base_schema.py
griptape/flow/schemas/drivers/__init__.py
griptape/flow/schemas/drivers/openai_prompt_driver_schema.py
griptape/flow/schemas/drivers/prompt_driver_schema.py
griptape/flow/schemas/memory/__init__.py
griptape/flow/schemas/memory/buffer_pipeline_memory_schema.py
griptape/flow/schemas/memory/pipeline_memory_schema.py
griptape/flow/schemas/memory/pipeline_run_schema.py
griptape/flow/schemas/memory/summary_pipeline_memory_schema.py
griptape/flow/schemas/polymorphic_schema.py
griptape/flow/schemas/rule_schema.py
griptape/flow/schemas/steps/__init__.py
griptape/flow/schemas/steps/prompt_step_schema.py
griptape/flow/schemas/steps/step_schema.py
griptape/flow/schemas/steps/toolkit_step_schema.py
griptape/flow/schemas/structures/__init__.py
griptape/flow/schemas/structures/pipeline_schema.py
griptape/flow/schemas/structures/structure_schema.py
griptape/flow/schemas/structures/workflow_schema.py
griptape_flow-0.12.1.dist-info/LICENSE
griptape_flow-0.12.1.dist-info/METADATA
griptape_flow-0.12.1.dist-info/WHEEL
griptape_flow-0.12.1.dist-info/RECORD
