Metadata-Version: 2.1
Name: griptape-flow
Version: 0.12.1
Summary: Python framework for LLM workflows and pipelines.
Home-page: https://github.com/griptape-ai/griptape-flow
License: Apache 2.0
Author: Griptape
Author-email: hello@griptape.ai
Requires-Python: >=3.9,<4.0
Classifier: License :: Other/Proprietary License
Classifier: Programming Language :: Python :: 3
Classifier: Programming Language :: Python :: 3.9
Classifier: Programming Language :: Python :: 3.10
Classifier: Programming Language :: Python :: 3.11
Requires-Dist: attrs (>=22)
Requires-Dist: cohere (>=4)
Requires-Dist: graphlib
Requires-Dist: griptape-core (>=0.9.2)
Requires-Dist: huggingface-hub (>=0.13)
Requires-Dist: jinja2 (>=3.1)
Requires-Dist: jsonschema (>=4)
Requires-Dist: marshmallow (>=3)
Requires-Dist: marshmallow-enum (>=1.5)
Requires-Dist: openai (>=0.27)
Requires-Dist: python-dotenv (>=0.21)
Requires-Dist: rich (>=13)
Requires-Dist: stopit
Requires-Dist: tiktoken (>=0.3)
Requires-Dist: torch (>=2)
Requires-Dist: transformers (>=4)
Project-URL: Repository, https://github.com/griptape-ai/griptape-flow
